mo/__init__.py
mo/core/__init__.py
mo/core/plugin/metadata_loader.py
mo/core/plugin/models/plugin.py
mo/core/plugin/models/properties.py
mo/core/plugin/models/semantic_version.py
mo/core/plugin/models/settings.py
mo/core/plugin/models/sys_platform.py
mo/core/plugin/models/validators.py
mo/core/utils/i18n.py
mo/modules/capture/__init__.py
mo/modules/capture/plugins/capture_plugin.py
mop/__init__.py
mop/build.py
mop/create.py
mop/templates/capture/.gitignore
mop/templates/capture/icons/dark.svg
mop/templates/capture/icons/light.svg
mop/templates/capture/locales/en/namespace.json
mop/templates/capture/metadata.json
mop/templates/capture/README.md
mop/templates/capture/requirements.txt
mop/templates/capture/src/__init__.py
mop/templates/capture/src/main.py
mop/templates/capture/src/properties.py
mop/test_capture.py
mop/utils/logger.py
mop/utils/path.py
mo_sdk-1.0.0.dist-info/entry_points.txt
mo_sdk-1.0.0.dist-info/METADATA
mo_sdk-1.0.0.dist-info/WHEEL
mo_sdk-1.0.0.dist-info/RECORD
