Metadata-Version: 2.3
Name: mo-sdk
Version: 1.0.0
Summary: Official SDK for building Multimodal Observer (MOo) plugins.
License: GPL-3.0-only
Keywords: sdk,mop,cli,tools,MOo,MO,plugin,multimodal,observer
Author: Matías Figueroa Contreras
Author-email: matias.figueroa.c@usach.cl
Requires-Python: >=3.12,<3.13
Classifier: License :: OSI Approved :: GNU General Public License v3 (GPLv3)
Classifier: Programming Language :: Python :: 3
Classifier: Programming Language :: Python :: 3.12
Requires-Dist: coverage (>=7.10.4,<8.0.0)
Requires-Dist: i18nice (>=0.16.0,<0.17.0)
Requires-Dist: pipreqs (>=0.5.0,<0.6.0)
Requires-Dist: pydantic (>=2.11.5,<3.0.0)
Requires-Dist: questionary (>=2.1.0,<3.0.0)
Project-URL: Repository, https://github.com/MultimodalObserver-2/mo-api-sdk
